{
  "builder-refer": "https://ravenherz.com/",
  "builder-title": "ravenherz",
  "company-address": "Saratov, Russian Federation",
  "company-email": "mailto://theravenherz@gmail.com",
  "company-phone": "",
  "company-social": "linkedin:ravenherz telegram:ravenherz soundcloud:ravenherz instagram:ravenherz youtube:ravenherz",
  "company-title": "ravenherz",
  "copyright-comment": "All rights reserved",
  "copyright-holder": "Aleksei Kolesnikov",
  "copyright-since": "2014",
  "date": "Tue Oct 30 2018 09:15:11 GMT+0400 (GMT+04:00)",
  "welcome-description": "<div class=\"text-region\">Primarily a software engineer. Hobbyist music-producer. Plays guitar since 15. Mostly Inspired by cool and dark jazz, soft piano. Prefers to work alone to keep everything under control</div><div class=\"biopicture\"><img src=\"./content-public/rhz-we-core/images/me.jpg\"></div>",
  "welcome-message": "Software engineer, musician, composer, sound-designer",
  "welcome-title": "Welcome<br>to safe place"
}
